rapidhtml/__init__.py
rapidhtml/app.py
rapidhtml/bases.py
rapidhtml/callbacks.py
rapidhtml/exceptions.py
rapidhtml/responses.py
rapidhtml/routing.py
rapidhtml/static/RapidHTML.svg
rapidhtml/style/__init__.py
rapidhtml/style/css.py
rapidhtml/tags.py
rapidhtml/utils/__init__.py
rapidhtml-0.1.1.dist-info/LICENSE
rapidhtml-0.1.1.dist-info/METADATA
rapidhtml-0.1.1.dist-info/WHEEL
rapidhtml-0.1.1.dist-info/RECORD
